LICENSE.md
MANIFEST.in
README.md
setup.cfg
setup.py
hxl_proxy/__init__.py
hxl_proxy/auth.py
hxl_proxy/caching.py
hxl_proxy/controllers.py
hxl_proxy/default_config.py
hxl_proxy/exceptions.py
hxl_proxy/filters.py
hxl_proxy/pcodes.py
hxl_proxy/preview.py
hxl_proxy/recipes.py
hxl_proxy/reverse_proxied.py
hxl_proxy/util.py
hxl_proxy/validate.py
hxl_proxy.egg-info/PKG-INFO
hxl_proxy.egg-info/SOURCES.txt
hxl_proxy.egg-info/dependency_links.txt
hxl_proxy.egg-info/requires.txt
hxl_proxy.egg-info/top_level.txt
hxl_proxy.egg-info/zip-safe
hxl_proxy/static/bootstrap/css/bootstrap-theme.css
hxl_proxy/static/bootstrap/css/bootstrap-theme.css.map
hxl_proxy/static/bootstrap/css/bootstrap-theme.min.css
hxl_proxy/static/bootstrap/css/bootstrap.css
hxl_proxy/static/bootstrap/css/bootstrap.css.map
hxl_proxy/static/bootstrap/css/bootstrap.min.css
hxl_proxy/static/bootstrap/fonts/glyphicons-halflings-regular.eot
hxl_proxy/static/bootstrap/fonts/glyphicons-halflings-regular.svg
hxl_proxy/static/bootstrap/fonts/glyphicons-halflings-regular.ttf
hxl_proxy/static/bootstrap/fonts/glyphicons-halflings-regular.woff
hxl_proxy/static/bootstrap/fonts/glyphicons-halflings-regular.woff2
hxl_proxy/static/bootstrap/js/bootstrap.js
hxl_proxy/static/bootstrap/js/bootstrap.min.js
hxl_proxy/static/bootstrap/js/npm.js
hxl_proxy/static/compat/html5shiv.min.js
hxl_proxy/static/compat/ie10-viewport-bug-workaround.js
hxl_proxy/static/compat/respond.min.js
hxl_proxy/static/hxl-proxy/hxl-proxy.css
hxl_proxy/static/hxl-proxy/hxl-proxy.js
hxl_proxy/static/hxl-proxy/icons/android-icon-144x144.png
hxl_proxy/static/hxl-proxy/icons/android-icon-192x192.png
hxl_proxy/static/hxl-proxy/icons/android-icon-36x36.png
hxl_proxy/static/hxl-proxy/icons/android-icon-48x48.png
hxl_proxy/static/hxl-proxy/icons/android-icon-72x72.png
hxl_proxy/static/hxl-proxy/icons/android-icon-96x96.png
hxl_proxy/static/hxl-proxy/icons/apple-icon-114x114.png
hxl_proxy/static/hxl-proxy/icons/apple-icon-120x120.png
hxl_proxy/static/hxl-proxy/icons/apple-icon-144x144.png
hxl_proxy/static/hxl-proxy/icons/apple-icon-152x152.png
hxl_proxy/static/hxl-proxy/icons/apple-icon-180x180.png
hxl_proxy/static/hxl-proxy/icons/apple-icon-57x57.png
