Metadata-Version: 2.1
Name: hxl-proxy
Version: 2.1.1
Summary: Flask-based web data proxy for the Humanitarian Exchange Language (HXL)
Home-page: UNKNOWN
Author: David Megginson
Author-email: megginson@un.org
License: Public Domain
Project-URL: Documentation, https://github.com/HXLStandard/hxl-proxy/wiki
Project-URL: GitHub, https://github.com/HXLStandard/hxl-proxy/
Project-URL: Changelog, https://github.com/HXLStandard/hxl-proxy/blob/prod/CHANGELOG
Keywords: data,hxl
Platform: UNKNOWN
Classifier: Framework :: Flask
Classifier: Programming Language :: Python :: 3
Requires-Python: >=3.7
License-File: LICENSE.md
